{
  "307815349699608577": [
    {
      "name": "⭐ Mimigal",
      "caught": 1
    },
    {
      "name": "⭐ Pyroli",
      "caught": 1
    },
    {
      "name": "Héliatronc",
      "caught": 8
    },
    {
      "name": "Foretress",
      "caught": 6
    },
    {
      "name": "Loupio",
      "caught": 6
    },
    {
      "name": "Magmar",
      "caught": 6
    },
    {
      "name": "Steelix",
      "caught": 6
    },
    {
      "name": "Abra",
      "caught": 5
    },
    {
      "name": "Arbok",
      "caught": 5
    },
    {
      "name": "Aéromite",
      "caught": 5
    },
    {
      "name": "Girafarig",
      "caught": 5
    },
    {
      "name": "Insolourdo",
      "caught": 5
    },
    {
      "name": "Minidraco",
      "caught": 5
    },
    {
      "name": "Qulbutoké",
      "caught": 5
    },
    {
      "name": "Rapasdepic",
      "caught": 5
    },
    {
      "name": "Zarbi",
      "caught": 5
    },
    {
      "name": "Akwakwak",
      "caught": 4
    },
    {
      "name": "Alakazam",
      "caught": 4
    },
    {
      "name": "Amonistar",
      "caught": 4
    },
    {
      "name": "Chétiflor",
      "caught": 4
    },
    {
      "name": "Cornèbre",
      "caught": 4
    },
    {
      "name": "Coxyclaque",
      "caught": 4
    },
    {
      "name": "Hoothoot",
      "caught": 4
    },
    {
      "name": "Hypotrempe",
      "caught": 4
    },
    {
      "name": "Joliflor",
      "caught": 4
    },
    {
      "name": "Kabutops",
      "caught": 4
    },
    {
      "name": "Lamantine",
      "caught": 4
    },
    {
      "name": "Magnéti",
      "caught": 4
    },
    {
      "name": "Ortide",
      "caught": 4
    },
    {
      "name": "Parasect",
      "caught": 4
    },
    {
      "name": "Pomdepik",
      "caught": 4
    },
    {
      "name": "Ponyta",
      "caught": 4
    },
    {
      "name": "Rattata",
      "caught": 4
    },
    {
      "name": "Rhinoféros",
      "caught": 4
    },
    {
      "name": "Simularbre",
      "caught": 4
    },
    {
      "name": "Smogogo",
      "caught": 4
    },
    {
      "name": "Tauros",
      "caught": 4
    },
    {
      "name": "Aspicot",
      "caught": 3
    },
    {
      "name": "Axoloto",
      "caught": 3
    },
    {
      "name": "Crustabri",
      "caught": 3
    },
    {
      "name": "Dardargnan",
      "caught": 3
    },
    {
      "name": "Fantominus",
      "caught": 3
    },
    {
      "name": "Feunard",
      "caught": 3
    },
    {
      "name": "Fouinette",
      "caught": 3
    },
    {
      "name": "Férossinge",
      "caught": 3
    },
    {
      "name": "Grodoudou",
      "caught": 3
    },
    {
      "name": "Kaiminus",
      "caught": 3
    },
    {
      "name": "Kicklee",
      "caught": 3
    },
    {
      "name": "Krabby",
      "caught": 3
    },
    {
      "name": "Lippoutou",
      "caught": 3
    },
    {
      "name": "Mackogneur",
      "caught": 3
    },
    {
      "name": "Marcacrin",
      "caught": 3
    },
    {
      "name": "Natu",
      "caught": 3
    },
    {
      "name": "Noeunoeuf",
      "caught": 3
    },
    {
      "name": "Papilusion",
      "caught": 3
    },
    {
      "name": "Persian",
      "caught": 3
    },
    {
      "name": "Poissoroy",
      "caught": 3
    },
    {
      "name": "Porygon",
      "caught": 3
    },
    {
      "name": "Reptincel",
      "caught": 3
    },
    {
      "name": "Roucool",
      "caught": 3
    },
    {
      "name": "Snubbull",
      "caught": 3
    },
    {
      "name": "Tentacruel",
      "caught": 3
    },
    {
      "name": "Togepi",
      "caught": 3
    },
    {
      "name": "Togetic",
      "caught": 3
    },
    {
      "name": "Toudoudou",
      "caught": 3
    },
    {
      "name": "Têtarte",
      "caught": 3
    },
    {
      "name": "Yanma",
      "caught": 3
    },
    {
      "name": "Airmure",
      "caught": 2
    },
    {
      "name": "Amonita",
      "caught": 2
    },
    {
      "name": "Aquali",
      "caught": 2
    },
    {
      "name": "Arcanin",
      "caught": 2
    },
    {
      "name": "Bulbizarre",
      "caught": 2
    },
    {
      "name": "Canarticho",
      "caught": 2
    },
    {
      "name": "Caninos",
      "caught": 2
    },
    {
      "name": "Capumain",
      "caught": 2
    },
    {
      "name": "Chrysacier",
      "caught": 2
    },
    {
      "name": "Cotovol",
      "caught": 2
    },
    {
      "name": "Debugant",
      "caught": 2
    },
    {
      "name": "Doduo",
      "caught": 2
    },
    {
      "name": "Écrémeuh",
      "caught": 2
    },
    {
      "name": "Ectoplasma",
      "caught": 2
    },
    {
      "name": "Électrode",
      "caught": 2
    },
    {
      "name": "Élektek",
      "caught": 2
    },
    {
      "name": "Empiflor",
      "caught": 2
    },
    {
      "name": "Évoli",
      "caught": 2
    },
    {
      "name": "Feuforêve",
      "caught": 2
    },
    {
      "name": "Flagadoss",
      "caught": 2
    },
    {
      "name": "Florizarre",
      "caught": 2
    },
    {
      "name": "Germignon",
      "caught": 2
    },
    {
      "name": "Granbull",
      "caught": 2
    },
    {
      "name": "Granivol",
      "caught": 2
    },
    {
      "name": "Gravalanch",
      "caught": 2
    },
    {
      "name": "Herbizarre",
      "caught": 2
    },
    {
      "name": "Hypnomade",
      "caught": 2
    },
    {
      "name": "Insécateur",
      "caught": 2
    },
    {
      "name": "Kabuto",
      "caught": 2
    },
    {
      "name": "Kokiyas",
      "caught": 2
    },
    {
      "name": "Lanturn",
      "caught": 2
    },
    {
      "name": "Machoc",
      "caught": 2
    },
    {
      "name": "Machopeur",
      "caught": 2
    },
    {
      "name": "Magicarpe",
      "caught": 2
    },
    {
      "name": "Magnéton",
      "caught": 2
    },
    {
      "name": "Maraiste",
      "caught": 2
    },
    {
      "name": "Mélo",
      "caught": 2
    },
    {
      "name": "Mélodelfe",
      "caught": 2
    },
    {
      "name": "Mélofée",
      "caught": 2
    },
    {
      "name": "Métamorph",
      "caught": 2
    },
    {
      "name": "Nidorina",
      "caught": 2
    },
    {
      "name": "Noadkoko",
      "caught": 2
    },
    {
      "name": "Noarfang",
      "caught": 2
    },
    {
      "name": "Nosferapti",
      "caught": 2
    },
    {
      "name": "Nostenfer",
      "caught": 2
    },
    {
      "name": "Octillery",
      "caught": 2
    },
    {
      "name": "Onix",
      "caught": 2
    },
    {
      "name": "Otaria",
      "caught": 2
    },
    {
      "name": "Paras",
      "caught": 2
    },
    {
      "name": "Phanpy",
      "caught": 2
    },
    {
      "name": "Piafabec",
      "caught": 2
    },
    {
      "name": "Pikachu",
      "caught": 2
    },
    {
      "name": "Queulorior",
      "caught": 2
    },
    {
      "name": "Raichu",
      "caught": 2
    },
    {
      "name": "Rhinocorne",
      "caught": 2
    },
    {
      "name": "Roigada",
      "caught": 2
    },
    {
      "name": "Roucoups",
      "caught": 2
    },
    {
      "name": "Sablaireau",
      "caught": 2
    },
    {
      "name": "Scorplane",
      "caught": 2
    },
    {
      "name": "Soporifik",
      "caught": 2
    },
    {
      "name": "Tygnon",
      "caught": 2
    },
    {
      "name": "Typhlosion",
      "caught": 2
    },
    {
      "name": "Ursaring",
      "caught": 2
    },
    {
      "name": "Voltali",
      "caught": 2
    },
    {
      "name": "Voltorbe",
      "caught": 2
    },
    {
      "name": "Xatu",
      "caught": 2
    },
    {
      "name": "Aligatueur",
      "caught": 1
    },
    {
      "name": "Boustiflor",
      "caught": 1
    },
    {
      "name": "Cadoizo",
      "caught": 1
    },
    {
      "name": "Carabaffe",
      "caught": 1
    },
    {
      "name": "Carapuce",
      "caught": 1
    },
    {
      "name": "Caratroc",
      "caught": 1
    },
    {
      "name": "Cerfrousse",
      "caught": 1
    },
    {
      "name": "Chenipan",
      "caught": 1
    },
    {
      "name": "Cizayox",
      "caught": 1
    },
    {
      "name": "Cochignon",
      "caught": 1
    },
    {
      "name": "Coconfort",
      "caught": 1
    },
    {
      "name": "Corayon",
      "caught": 1
    },
    {
      "name": "Coxy",
      "caught": 1
    },
    {
      "name": "Crocodil",
      "caught": 1
    },
    {
      "name": "Dodrio",
      "caught": 1
    },
    {
      "name": "Draco",
      "caught": 1
    },
    {
      "name": "Démanta",
      "caught": 1
    },
    {
      "name": "Embrylex",
      "caught": 1
    },
    {
      "name": "Feurisson",
      "caught": 1
    },
    {
      "name": "Galopa",
      "caught": 1
    },
    {
      "name": "Goupix",
      "caught": 1
    },
    {
      "name": "Hypocéan",
      "caught": 1
    },
    {
      "name": "Kadabra",
      "caught": 1
    },
    {
      "name": "Kangourex",
      "caught": 1
    },
    {
      "name": "Kapoera",
      "caught": 1
    },
    {
      "name": "Lainergie",
      "caught": 1
    },
    {
      "name": "Leveinard",
      "caught": 1
    },
    {
      "name": "Lokhlass",
      "caught": 1
    },
    {
      "name": "M. Mime",
      "caught": 1
    },
    {
      "name": "M. Mime de Galar",
      "caught": 1
    },
    {
      "name": "Malosse",
      "caught": 1
    },
    {
      "name": "Marill",
      "caught": 1
    },
    {
      "name": "Mentali",
      "caught": 1
    },
    {
      "name": "Miaouss",
      "caught": 1
    },
    {
      "name": "Migalos",
      "caught": 1
    },
    {
      "name": "Mimigal",
      "caught": 1
    },
    {
      "name": "Mimitoss",
      "caught": 1
    },
    {
      "name": "Méganium",
      "caught": 1
    },
    {
      "name": "Nidoking",
      "caught": 1
    },
    {
      "name": "Nidoqueen",
      "caught": 1
    },
    {
      "name": "Nidorino",
      "caught": 1
    },
    {
      "name": "Noctali",
      "caught": 1
    },
    {
      "name": "Nosferalto",
      "caught": 1
    },
    {
      "name": "Pharamp",
      "caught": 1
    },
    {
      "name": "Poissirène",
      "caught": 1
    },
    {
      "name": "Pyroli",
      "caught": 1
    },
    {
      "name": "Qwilfish",
      "caught": 1
    },
    {
      "name": "Rafflesia",
      "caught": 1
    },
    {
      "name": "Ramoloss de Galar",
      "caught": 1
    },
    {
      "name": "Rattatac",
      "caught": 1
    },
    {
      "name": "Rondoudou",
      "caught": 1
    },
    {
      "name": "Ronflex",
      "caught": 1
    },
    {
      "name": "Sabelette",
      "caught": 1
    },
    {
      "name": "Saquedeneu",
      "caught": 1
    },
    {
      "name": "Scarabrute",
      "caught": 1
    },
    {
      "name": "Scarhino",
      "caught": 1
    },
    {
      "name": "Smogo",
      "caught": 1
    },
    {
      "name": "Smogogo de Galar",
      "caught": 1
    },
    {
      "name": "Staross",
      "caught": 1
    },
    {
      "name": "Tarpaud",
      "caught": 1
    },
    {
      "name": "Tartard",
      "caught": 1
    },
    {
      "name": "Taupiqueur",
      "caught": 1
    },
    {
      "name": "Tentacool",
      "caught": 1
    },
    {
      "name": "Triopikeur",
      "caught": 1
    },
    {
      "name": "Tyranocif",
      "caught": 1
    },
    {
      "name": "Volcaropod",
      "caught": 1
    },
    {
      "name": "Wattouat",
      "caught": 1
    },
    {
      "name": "Ymphect",
      "caught": 1
    }
  ],
  "679673968482975799": [
    {
      "name": "Chrysacier",
      "caught": 1
    }
  ],
  "638640935021838347": [
    {
      "name": "⭐ Lippoutou",
      "caught": 1
    },
    {
      "name": "Soporifik",
      "caught": 5
    },
    {
      "name": "Chenipan",
      "caught": 4
    },
    {
      "name": "Excelangue",
      "caught": 4
    },
    {
      "name": "Farfuret",
      "caught": 4
    },
    {
      "name": "Galopa",
      "caught": 4
    },
    {
      "name": "Insécateur",
      "caught": 4
    },
    {
      "name": "Kadabra",
      "caught": 4
    },
    {
      "name": "Lanturn",
      "caught": 4
    },
    {
      "name": "Magnéti",
      "caught": 4
    },
    {
      "name": "Sablaireau",
      "caught": 4
    },
    {
      "name": "Saquedeneu",
      "caught": 4
    },
    {
      "name": "Tentacruel",
      "caught": 4
    },
    {
      "name": "Arcanin",
      "caught": 3
    },
    {
      "name": "Chétiflor",
      "caught": 3
    },
    {
      "name": "Insolourdo",
      "caught": 3
    },
    {
      "name": "Lamantine",
      "caught": 3
    },
    {
      "name": "Mimigal",
      "caught": 3
    },
    {
      "name": "Nosferapti",
      "caught": 3
    },
    {
      "name": "Onix",
      "caught": 3
    },
    {
      "name": "Ossatueur",
      "caught": 3
    },
    {
      "name": "Parasect",
      "caught": 3
    },
    {
      "name": "Ponyta",
      "caught": 3
    },
    {
      "name": "Ptéra",
      "caught": 3
    },
    {
      "name": "Qwilfish",
      "caught": 3
    },
    {
      "name": "Sabelette",
      "caught": 3
    },
    {
      "name": "Steelix",
      "caught": 3
    },
    {
      "name": "Tarpaud",
      "caught": 3
    },
    {
      "name": "Taupiqueur",
      "caught": 3
    },
    {
      "name": "Teddiursa",
      "caught": 3
    },
    {
      "name": "Axoloto",
      "caught": 2
    },
    {
      "name": "Azumarill",
      "caught": 2
    },
    {
      "name": "Canarticho",
      "caught": 2
    },
    {
      "name": "Cochignon",
      "caught": 2
    },
    {
      "name": "Coconfort",
      "caught": 2
    },
    {
      "name": "Cornèbre",
      "caught": 2
    },
    {
      "name": "Coxyclaque",
      "caught": 2
    },
    {
      "name": "Debugant",
      "caught": 2
    },
    {
      "name": "Doduo",
      "caught": 2
    },
    {
      "name": "Ectoplasma",
      "caught": 2
    },
    {
      "name": "Électrode",
      "caught": 2
    },
    {
      "name": "Élektek",
      "caught": 2
    },
    {
      "name": "Feuforêve",
      "caught": 2
    },
    {
      "name": "Feurisson",
      "caught": 2
    },
    {
      "name": "Foretress",
      "caught": 2
    },
    {
      "name": "Férossinge",
      "caught": 2
    },
    {
      "name": "Hypocéan",
      "caught": 2
    },
    {
      "name": "Hypotrempe",
      "caught": 2
    },
    {
      "name": "Joliflor",
      "caught": 2
    },
    {
      "name": "Kabuto",
      "caught": 2
    },
    {
      "name": "Kabutops",
      "caught": 2
    },
    {
      "name": "Kokiyas",
      "caught": 2
    },
    {
      "name": "Krabby",
      "caught": 2
    },
    {
      "name": "Leuphorie",
      "caught": 2
    },
    {
      "name": "Loupio",
      "caught": 2
    },
    {
      "name": "M. Mime de Galar",
      "caught": 2
    },
    {
      "name": "Mackogneur",
      "caught": 2
    },
    {
      "name": "Magicarpe",
      "caught": 2
    },
    {
      "name": "Minidraco",
      "caught": 2
    },
    {
      "name": "Mélo",
      "caught": 2
    },
    {
      "name": "Mélodelfe",
      "caught": 2
    },
    {
      "name": "Nidorina",
      "caught": 2
    },
    {
      "name": "Nostenfer",
      "caught": 2
    },
    {
      "name": "Papilusion",
      "caught": 2
    },
    {
      "name": "Poissirène",
      "caught": 2
    },
    {
      "name": "Porygon",
      "caught": 2
    },
    {
      "name": "Ptitard",
      "caught": 2
    },
    {
      "name": "Pyroli",
      "caught": 2
    },
    {
      "name": "Queulorior",
      "caught": 2
    },
    {
      "name": "Rhinocorne",
      "caught": 2
    },
    {
      "name": "Roucool",
      "caught": 2
    },
    {
      "name": "Roucoups",
      "caught": 2
    },
    {
      "name": "Salamèche",
      "caught": 2
    },
    {
      "name": "Scorplane",
      "caught": 2
    },
    {
      "name": "Snubbull",
      "caught": 2
    },
    {
      "name": "Tartard",
      "caught": 2
    },
    {
      "name": "Tentacool",
      "caught": 2
    },
    {
      "name": "Triopikeur",
      "caught": 2
    },
    {
      "name": "Typhlosion",
      "caught": 2
    },
    {
      "name": "Xatu",
      "caught": 2
    },
    {
      "name": "Abra",
      "caught": 1
    },
    {
      "name": "Akwakwak",
      "caught": 1
    },
    {
      "name": "Aligatueur",
      "caught": 1
    },
    {
      "name": "Amonita",
      "caught": 1
    },
    {
      "name": "Aquali",
      "caught": 1
    },
    {
      "name": "Aspicot",
      "caught": 1
    },
    {
      "name": "Aéromite",
      "caught": 1
    },
    {
      "name": "Bulbizarre",
      "caught": 1
    },
    {
      "name": "Cadoizo",
      "caught": 1
    },
    {
      "name": "Caninos",
      "caught": 1
    },
    {
      "name": "Capumain",
      "caught": 1
    },
    {
      "name": "Carapuce",
      "caught": 1
    },
    {
      "name": "Caratroc",
      "caught": 1
    },
    {
      "name": "Chrysacier",
      "caught": 1
    },
    {
      "name": "Colossinge",
      "caught": 1
    },
    {
      "name": "Crustabri",
      "caught": 1
    },
    {
      "name": "Dracaufeu",
      "caught": 1
    },
    {
      "name": "Draco",
      "caught": 1
    },
    {
      "name": "Démanta",
      "caught": 1
    },
    {
      "name": "Démolosse",
      "caught": 1
    },
    {
      "name": "Empiflor",
      "caught": 1
    },
    {
      "name": "Fantominus",
      "caught": 1
    },
    {
      "name": "Feunard",
      "caught": 1
    },
    {
      "name": "Florizarre",
      "caught": 1
    },
    {
      "name": "Germignon",
      "caught": 1
    },
    {
      "name": "Girafarig",
      "caught": 1
    },
    {
      "name": "Granbull",
      "caught": 1
    },
    {
      "name": "Granivol",
      "caught": 1
    },
    {
      "name": "Grodoudou",
      "caught": 1
    },
    {
      "name": "Héliatronc",
      "caught": 1
    },
    {
      "name": "Héricendre",
      "caught": 1
    },
    {
      "name": "Kapoera",
      "caught": 1
    },
    {
      "name": "Krabboss",
      "caught": 1
    },
    {
      "name": "Leveinard",
      "caught": 1
    },
    {
      "name": "Lippouti",
      "caught": 1
    },
    {
      "name": "Léviator",
      "caught": 1
    },
    {
      "name": "Machopeur",
      "caught": 1
    },
    {
      "name": "Magby",
      "caught": 1
    },
    {
      "name": "Magmar",
      "caught": 1
    },
    {
      "name": "Malosse",
      "caught": 1
    },
    {
      "name": "Maraiste",
      "caught": 1
    },
    {
      "name": "Marcacrin",
      "caught": 1
    },
    {
      "name": "Migalos",
      "caught": 1
    },
    {
      "name": "Mystherbe",
      "caught": 1
    },
    {
      "name": "Méganium",
      "caught": 1
    },
    {
      "name": "Mélofée",
      "caught": 1
    },
    {
      "name": "Métamorph",
      "caught": 1
    },
    {
      "name": "Nidoking",
      "caught": 1
    },
    {
      "name": "Nidoqueen",
      "caught": 1
    },
    {
      "name": "Nidoran♂",
      "caught": 1
    },
    {
      "name": "Nidorino",
      "caught": 1
    },
    {
      "name": "Noadkoko d'Alola",
      "caught": 1
    },
    {
      "name": "Noarfang",
      "caught": 1
    },
    {
      "name": "Noctali",
      "caught": 1
    },
    {
      "name": "Octillery",
      "caught": 1
    },
    {
      "name": "Osselait",
      "caught": 1
    },
    {
      "name": "Phanpy",
      "caught": 1
    },
    {
      "name": "Piafabec",
      "caught": 1
    },
    {
      "name": "Pichu",
      "caught": 1
    },
    {
      "name": "Pikachu",
      "caught": 1
    },
    {
      "name": "Poissoroy",
      "caught": 1
    },
    {
      "name": "Pomdepik",
      "caught": 1
    },
    {
      "name": "Psykokwak",
      "caught": 1
    },
    {
      "name": "Qulbutoké",
      "caught": 1
    },
    {
      "name": "Racaillou",
      "caught": 1
    },
    {
      "name": "Raichu",
      "caught": 1
    },
    {
      "name": "Ramoloss",
      "caught": 1
    },
    {
      "name": "Rattata",
      "caught": 1
    },
    {
      "name": "Rondoudou",
      "caught": 1
    },
    {
      "name": "Ronflex",
      "caught": 1
    },
    {
      "name": "Rémoraid",
      "caught": 1
    },
    {
      "name": "Scarabrute",
      "caught": 1
    },
    {
      "name": "Scarhino",
      "caught": 1
    },
    {
      "name": "Simularbre",
      "caught": 1
    },
    {
      "name": "Smogo",
      "caught": 1
    },
    {
      "name": "Spectrum",
      "caught": 1
    },
    {
      "name": "Staross",
      "caught": 1
    },
    {
      "name": "Tauros",
      "caught": 1
    },
    {
      "name": "Togetic",
      "caught": 1
    },
    {
      "name": "Toudoudou",
      "caught": 1
    },
    {
      "name": "Tournegrin",
      "caught": 1
    },
    {
      "name": "Tygnon",
      "caught": 1
    },
    {
      "name": "Têtarte",
      "caught": 1
    },
    {
      "name": "Voltali",
      "caught": 1
    },
    {
      "name": "Wattouat",
      "caught": 1
    }
  ],
  "685833203197411339": [
    {
      "name": "Dodrio",
      "caught": 5
    },
    {
      "name": "Pikachu",
      "caught": 5
    },
    {
      "name": "Canarticho",
      "caught": 4
    },
    {
      "name": "Caratroc",
      "caught": 4
    },
    {
      "name": "Cornèbre",
      "caught": 4
    },
    {
      "name": "Hyporoi",
      "caught": 4
    },
    {
      "name": "Hypotrempe",
      "caught": 4
    },
    {
      "name": "Insolourdo",
      "caught": 4
    },
    {
      "name": "Magnéton",
      "caught": 4
    },
    {
      "name": "Poissirène",
      "caught": 4
    },
    {
      "name": "Roucool",
      "caught": 4
    },
    {
      "name": "Scorplane",
      "caught": 4
    },
    {
      "name": "Capumain",
      "caught": 3
    },
    {
      "name": "Carapuce",
      "caught": 3
    },
    {
      "name": "Fantominus",
      "caught": 3
    },
    {
      "name": "Granbull",
      "caught": 3
    },
    {
      "name": "Grotadmorv",
      "caught": 3
    },
    {
      "name": "Héricendre",
      "caught": 3
    },
    {
      "name": "Lokhlass",
      "caught": 3
    },
    {
      "name": "Machopeur",
      "caught": 3
    },
    {
      "name": "Marill",
      "caught": 3
    },
    {
      "name": "Minidraco",
      "caught": 3
    },
    {
      "name": "Natu",
      "caught": 3
    },
    {
      "name": "Nosferalto",
      "caught": 3
    },
    {
      "name": "Otaria",
      "caught": 3
    },
    {
      "name": "Poissoroy",
      "caught": 3
    },
    {
      "name": "Porygon",
      "caught": 3
    },
    {
      "name": "Ptitard",
      "caught": 3
    },
    {
      "name": "Reptincel",
      "caught": 3
    },
    {
      "name": "Rondoudou",
      "caught": 3
    },
    {
      "name": "Ronflex",
      "caught": 3
    },
    {
      "name": "Tentacool",
      "caught": 3
    },
    {
      "name": "Wattouat",
      "caught": 3
    },
    {
      "name": "Xatu",
      "caught": 3
    },
    {
      "name": "Akwakwak",
      "caught": 2
    },
    {
      "name": "Amonistar",
      "caught": 2
    },
    {
      "name": "Aéromite",
      "caught": 2
    },
    {
      "name": "Boustiflor",
      "caught": 2
    },
    {
      "name": "Cadoizo",
      "caught": 2
    },
    {
      "name": "Colossinge",
      "caught": 2
    },
    {
      "name": "Corayon",
      "caught": 2
    },
    {
      "name": "Cotovol",
      "caught": 2
    },
    {
      "name": "Coxy",
      "caught": 2
    },
    {
      "name": "Ectoplasma",
      "caught": 2
    },
    {
      "name": "Feunard d'Alola",
      "caught": 2
    },
    {
      "name": "Foretress",
      "caught": 2
    },
    {
      "name": "Férossinge",
      "caught": 2
    },
    {
      "name": "Gravalanch",
      "caught": 2
    },
    {
      "name": "Hoothoot",
      "caught": 2
    },
    {
      "name": "Insécateur",
      "caught": 2
    },
    {
      "name": "Joliflor",
      "caught": 2
    },
    {
      "name": "Kangourex",
      "caught": 2
    },
    {
      "name": "Leveinard",
      "caught": 2
    },
    {
      "name": "Lippoutou",
      "caught": 2
    },
    {
      "name": "Loupio",
      "caught": 2
    },
    {
      "name": "Magicarpe",
      "caught": 2
    },
    {
      "name": "Malosse",
      "caught": 2
    },
    {
      "name": "Nidoran♀",
      "caught": 2
    },
    {
      "name": "Nidorino",
      "caught": 2
    },
    {
      "name": "Noadkoko",
      "caught": 2
    },
    {
      "name": "Nosferapti",
      "caught": 2
    },
    {
      "name": "Osselait",
      "caught": 2
    },
    {
      "name": "Parasect",
      "caught": 2
    },
    {
      "name": "Phanpy",
      "caught": 2
    },
    {
      "name": "Pomdepik",
      "caught": 2
    },
    {
      "name": "Ponyta",
      "caught": 2
    },
    {
      "name": "Qulbutoké",
      "caught": 2
    },
    {
      "name": "Qwilfish",
      "caught": 2
    },
    {
      "name": "Ramoloss",
      "caught": 2
    },
    {
      "name": "Roucoups",
      "caught": 2
    },
    {
      "name": "Scarabrute",
      "caught": 2
    },
    {
      "name": "Smogo",
      "caught": 2
    },
    {
      "name": "Snubbull",
      "caught": 2
    },
    {
      "name": "Tadmorv",
      "caught": 2
    },
    {
      "name": "Tarpaud",
      "caught": 2
    },
    {
      "name": "Taupiqueur",
      "caught": 2
    },
    {
      "name": "Tournegrin",
      "caught": 2
    },
    {
      "name": "Têtarte",
      "caught": 2
    },
    {
      "name": "Yanma",
      "caught": 2
    },
    {
      "name": "Ymphect",
      "caught": 2
    },
    {
      "name": "Abo",
      "caught": 1
    },
    {
      "name": "Abra",
      "caught": 1
    },
    {
      "name": "Airmure",
      "caught": 1
    },
    {
      "name": "Aligatueur",
      "caught": 1
    },
    {
      "name": "Amonita",
      "caught": 1
    },
    {
      "name": "Arcanin",
      "caught": 1
    },
    {
      "name": "Aspicot",
      "caught": 1
    },
    {
      "name": "Axoloto",
      "caught": 1
    },
    {
      "name": "Azumarill",
      "caught": 1
    },
    {
      "name": "Bulbizarre",
      "caught": 1
    },
    {
      "name": "Carabaffe",
      "caught": 1
    },
    {
      "name": "Chenipan",
      "caught": 1
    },
    {
      "name": "Chétiflor",
      "caught": 1
    },
    {
      "name": "Cochignon",
      "caught": 1
    },
    {
      "name": "Crocodil",
      "caught": 1
    },
    {
      "name": "Crustabri",
      "caught": 1
    },
    {
      "name": "Debugant",
      "caught": 1
    },
    {
      "name": "Donphan",
      "caught": 1
    },
    {
      "name": "Draco",
      "caught": 1
    },
    {
      "name": "Dracolosse",
      "caught": 1
    },
    {
      "name": "Démanta",
      "caught": 1
    },
    {
      "name": "Écrémeuh",
      "caught": 1
    },
    {
      "name": "Embrylex",
      "caught": 1
    },
    {
      "name": "Évoli",
      "caught": 1
    },
    {
      "name": "Excelangue",
      "caught": 1
    },
    {
      "name": "Farfuret",
      "caught": 1
    },
    {
      "name": "Feuforêve",
      "caught": 1
    },
    {
      "name": "Feunard",
      "caught": 1
    },
    {
      "name": "Feurisson",
      "caught": 1
    },
    {
      "name": "Flagadoss",
      "caught": 1
    },
    {
      "name": "Fouinar",
      "caught": 1
    },
    {
      "name": "Fouinette",
      "caught": 1
    },
    {
      "name": "Galopa",
      "caught": 1
    },
    {
      "name": "Galopa de Galar",
      "caught": 1
    },
    {
      "name": "Goupix",
      "caught": 1
    },
    {
      "name": "Granivol",
      "caught": 1
    },
    {
      "name": "Hypocéan",
      "caught": 1
    },
    {
      "name": "Héliatronc",
      "caught": 1
    },
    {
      "name": "Kabutops",
      "caught": 1
    },
    {
      "name": "Kicklee",
      "caught": 1
    },
    {
      "name": "Kokiyas",
      "caught": 1
    },
    {
      "name": "Lamantine",
      "caught": 1
    },
    {
      "name": "Lanturn",
      "caught": 1
    },
    {
      "name": "Lippouti",
      "caught": 1
    },
    {
      "name": "Léviator",
      "caught": 1
    },
    {
      "name": "M. Mime",
      "caught": 1
    },
    {
      "name": "Machoc",
      "caught": 1
    },
    {
      "name": "Magby",
      "caught": 1
    },
    {
      "name": "Maraiste",
      "caught": 1
    },
    {
      "name": "Marcacrin",
      "caught": 1
    },
    {
      "name": "Mimitoss",
      "caught": 1
    },
    {
      "name": "Méganium",
      "caught": 1
    },
    {
      "name": "Mélo",
      "caught": 1
    },
    {
      "name": "Métamorph",
      "caught": 1
    },
    {
      "name": "Nidoking",
      "caught": 1
    },
    {
      "name": "Nidoran♂",
      "caught": 1
    },
    {
      "name": "Nidorina",
      "caught": 1
    },
    {
      "name": "Noarfang",
      "caught": 1
    },
    {
      "name": "Onix",
      "caught": 1
    },
    {
      "name": "Ortide",
      "caught": 1
    },
    {
      "name": "Paras",
      "caught": 1
    },
    {
      "name": "Persian",
      "caught": 1
    },
    {
      "name": "Ponyta de Galar",
      "caught": 1
    },
    {
      "name": "Psykokwak",
      "caught": 1
    },
    {
      "name": "Racaillou",
      "caught": 1
    },
    {
      "name": "Raikou",
      "caught": 1
    },
    {
      "name": "Rapasdepic",
      "caught": 1
    },
    {
      "name": "Rattata",
      "caught": 1
    },
    {
      "name": "Rattatac",
      "caught": 1
    },
    {
      "name": "Rattatac d'Alola",
      "caught": 1
    },
    {
      "name": "Rhinocorne",
      "caught": 1
    },
    {
      "name": "Rhinoféros",
      "caught": 1
    },
    {
      "name": "Roigada",
      "caught": 1
    },
    {
      "name": "Roucarnage",
      "caught": 1
    },
    {
      "name": "Sabelette",
      "caught": 1
    },
    {
      "name": "Salamèche",
      "caught": 1
    },
    {
      "name": "Scarhino",
      "caught": 1
    },
    {
      "name": "Smogogo",
      "caught": 1
    },
    {
      "name": "Soporifik",
      "caught": 1
    },
    {
      "name": "Spectrum",
      "caught": 1
    },
    {
      "name": "Stari",
      "caught": 1
    },
    {
      "name": "Staross",
      "caught": 1
    },
    {
      "name": "Taupiqueur d'Alola",
      "caught": 1
    },
    {
      "name": "Togepi",
      "caught": 1
    },
    {
      "name": "Togetic",
      "caught": 1
    },
    {
      "name": "Triopikeur",
      "caught": 1
    },
    {
      "name": "Tygnon",
      "caught": 1
    },
    {
      "name": "Typhlosion",
      "caught": 1
    },
    {
      "name": "Tyranocif",
      "caught": 1
    },
    {
      "name": "Volcaropod",
      "caught": 1
    },
    {
      "name": "Zarbi",
      "caught": 1
    }
  ],
  "408246564553752577": [
    {
      "name": "Mimigal",
      "caught": 1
    }
  ],
  "329576537323995138": [
    {
      "name": "Canarticho",
      "caught": 1
    },
    {
      "name": "Goupix",
      "caught": 1
    },
    {
      "name": "Poissirène",
      "caught": 1
    }
  ],
  "407593297855512586": [
    {
      "name": "Goupix",
      "caught": 2
    },
    {
      "name": "Smogo",
      "caught": 2
    },
    {
      "name": "Chétiflor",
      "caught": 1
    },
    {
      "name": "Coconfort",
      "caught": 1
    },
    {
      "name": "Doduo",
      "caught": 1
    },
    {
      "name": "Feuforêve",
      "caught": 1
    },
    {
      "name": "Fouinette",
      "caught": 1
    },
    {
      "name": "Girafarig",
      "caught": 1
    },
    {
      "name": "Insécateur",
      "caught": 1
    },
    {
      "name": "Kabuto",
      "caught": 1
    },
    {
      "name": "M. Mime",
      "caught": 1
    },
    {
      "name": "Magby",
      "caught": 1
    },
    {
      "name": "Magmar",
      "caught": 1
    },
    {
      "name": "Miaouss",
      "caught": 1
    },
    {
      "name": "Minidraco",
      "caught": 1
    },
    {
      "name": "Pichu",
      "caught": 1
    },
    {
      "name": "Ptéra",
      "caught": 1
    },
    {
      "name": "Qwilfish",
      "caught": 1
    },
    {
      "name": "Rattata",
      "caught": 1
    },
    {
      "name": "Sablaireau",
      "caught": 1
    },
    {
      "name": "Spectrum",
      "caught": 1
    },
    {
      "name": "Staross",
      "caught": 1
    },
    {
      "name": "Togetic",
      "caught": 1
    },
    {
      "name": "Têtarte",
      "caught": 1
    },
    {
      "name": "Voltorbe",
      "caught": 1
    }
  ],
  "510493665693794315": [
    {
      "name": "Ptéra",
      "caught": 1
    }
  ]
}